forecast/__init__.py
forecast/api.py
forecast/cli.py
forecast/models.py
forecast/requestor.py
pyforecast-0.1.4.dist-info/METADATA
pyforecast-0.1.4.dist-info/RECORD
pyforecast-0.1.4.dist-info/WHEEL
pyforecast-0.1.4.dist-info/entry_points.txt
pyforecast-0.1.4.dist-info/top_level.txt
