Metadata-Version: 2.1
Name: pyforecast
Version: 0.1.4
Summary: Python binding for Forecast Harverst API
Home-page: https://github.com/vafliik/pyforecast
Author: Pavel Pribyl
Author-email: pribyl.pavel@gmail.com
License: Apache Software License 2.0
Keywords: pyforecast
Platform: UNKNOWN
Classifier: Development Status :: 2 - Pre-Alpha
Classifier: Intended Audience :: Developers
Classifier: License :: OSI Approved :: Apache Software License
Classifier: Natural Language :: English
Classifier: Programming Language :: Python :: 3
Classifier: Programming Language :: Python :: 3.4
Classifier: Programming Language :: Python :: 3.5
Classifier: Programming Language :: Python :: 3.6
Requires-Dist: Click (>=6.0)
Requires-Dist: requests (>=2.18.0)
Requires-Dist: requests-cache (>=0.4.13)
